{
  "name": "Broadband",
  "type": "ABSTRACT_CONCEPT",
  "id": {
    "group": 50,
    "item": 7890
  },
  "claims": [
    {
      "predicate": "DEFINED_AS",
      "object": "communication of multiple data streams using a range of frequencies on a shared physical media",
      "temporal": {
        "valid_from": "ORIGIN",
        "valid_until": "PRESENT",
        "event": null
      },
      "epistemic": {
        "confidence": 0.9,
        "status": "SETTLED",
        "source_type": "ACADEMIC"
      }
    },
    {
      "predicate": "RELATED_TO",
      "object": "data (50, 1235)",
      "epistemic": {
        "confidence": 0.9,
        "status": "AUTO_GENERATED",
        "source_type": "RELATION_BUILDER"
      }
    }
  ],
  "surface_layer": {
    "definition": "Communication of multiple data streams over a range of frequencies.",
    "common_uses": [
      "high-speed internet access",
      "cable television"
    ]
  },
  "deep_layer": {
    "mechanism": "Multiple data streams are modulated onto different carrier frequencies and transmitted simultaneously.",
    "origin": "Developed to increase data transmission capacity."
  },
  "instance_layer": {
    "examples": [
      "Cable TV",
      "Internet",
      "Phone"
    ]
  },
  "facets": {
    "STRUCTURAL": {
      "visual_features": [],
      "shape": [],
      "composition": [],
      "parts": [],
      "relations": []
    },
    "SPATIAL": {
      "location": null,
      "coordinates": [],
      "connected_to": [],
      "contained_in": null
    },
    "FUNCTION": {
      "roles": [],
      "capabilities": []
    }
  },
  "epistemic_metadata": {
    "source": "PDF Communications and Protocol Basics - IEEE",
    "citations": [
      "https://www.ewh.ieee.org/r3/nashville/events/2019/IEEE+Meeting+Presentation+-+Communications+Basics+2019-02-05.pdf"
    ]
  }
}