{
  "name": "Cellular Necrosis",
  "type": "LIVING_SYSTEM",
  "id": {
    "group": 21,
    "item": 7890
  },
  "claims": [
    {
      "predicate": "CAUSED_BY",
      "object": "large amounts of mitochondrial calcium in the setting of ischemia-reperfusion injury",
      "temporal": {
        "valid_from": null,
        "valid_until": null,
        "event": null
      },
      "epistemic": {
        "confidence": 0.9,
        "status": "SETTLED",
        "source_type": "ACADEMIC"
      }
    },
    {
      "predicate": "RELATED_TO",
      "object": "cell (21, 1001)",
      "epistemic": {
        "confidence": 0.9,
        "status": "AUTO_GENERATED",
        "source_type": "RELATION_BUILDER"
      }
    }
  ],
  "surface_layer": {
    "definition": "Cell death due to injury.",
    "common_uses": []
  },
  "deep_layer": {
    "mechanism": null,
    "origin": null
  },
  "instance_layer": {
    "examples": []
  },
  "facets": {},
  "epistemic_metadata": {
    "source": "Set Automatically",
    "citations": []
  }
}