{
  "name": "Dual In-Line Package",
  "type": "INANIMATE_OBJECT",
  "id": {
    "group": 21,
    "item": 1002
  },
  "claims": [
    {
      "predicate": "IS_A",
      "object": "Electronic component package",
      "temporal": {
        "valid_from": "ORIGIN",
        "valid_until": "PRESENT",
        "event": null
      },
      "epistemic": {
        "confidence": 0.9,
        "status": "SETTLED",
        "source_type": "ACADEMIC"
      }
    },
    {
      "predicate": "HAS_PART",
      "object": "Rectangular housing",
      "temporal": {
        "valid_from": "ORIGIN",
        "valid_until": "PRESENT",
        "event": null
      },
      "epistemic": {
        "confidence": 0.9,
        "status": "SETTLED",
        "source_type": "ACADEMIC"
      }
    },
    {
      "predicate": "HAS_PART",
      "object": "Electrical connecting pins",
      "temporal": {
        "valid_from": "ORIGIN",
        "valid_until": "PRESENT",
        "event": null
      },
      "epistemic": {
        "confidence": 0.9,
        "status": "SETTLED",
        "source_type": "ACADEMIC"
      }
    },
    {
      "predicate": "HAS_PART",
      "object": "Device die",
      "temporal": {
        "valid_from": "ORIGIN",
        "valid_until": "PRESENT",
        "event": null
      },
      "epistemic": {
        "confidence": 0.8,
        "status": "SETTLED",
        "source_type": "ACADEMIC"
      }
    },
    {
      "predicate": "MADE_OF",
      "object": "Opaque molded epoxy plastic",
      "temporal": {
        "valid_from": "ORIGIN",
        "valid_until": "PRESENT",
        "event": null
      },
      "epistemic": {
        "confidence": 0.7,
        "status": "SETTLED",
        "source_type": "ACADEMIC"
      }
    },
    {
      "predicate": "MADE_OF",
      "object": "Tin-plated lead frame",
      "temporal": {
        "valid_from": "ORIGIN",
        "valid_until": "PRESENT",
        "event": null
      },
      "epistemic": {
        "confidence": 0.7,
        "status": "SETTLED",
        "source_type": "ACADEMIC"
      }
    },
    {
      "predicate": "MADE_OF",
      "object": "Silver-plated lead frame",
      "temporal": {
        "valid_from": "ORIGIN",
        "valid_until": "PRESENT",
        "event": null
      },
      "epistemic": {
        "confidence": 0.7,
        "status": "SETTLED",
        "source_type": "ACADEMIC"
      }
    },
    {
      "predicate": "MADE_OF",
      "object": "Gold-plated lead frame",
      "temporal": {
        "valid_from": "ORIGIN",
        "valid_until": "PRESENT",
        "event": null
      },
      "epistemic": {
        "confidence": 0.7,
        "status": "SETTLED",
        "source_type": "ACADEMIC"
      }
    },
    {
      "predicate": "USED_FOR",
      "object": "Connecting electronic components",
      "temporal": {
        "valid_from": "ORIGIN",
        "valid_until": "PRESENT",
        "event": null
      },
      "epistemic": {
        "confidence": 0.8,
        "status": "SETTLED",
        "source_type": "ACADEMIC"
      }
    },
    {
      "predicate": "LOCATED_AT",
      "object": "Printed circuit board",
      "temporal": {
        "valid_from": "ORIGIN",
        "valid_until": "PRESENT",
        "event": null
      },
      "epistemic": {
        "confidence": 0.7,
        "status": "SETTLED",
        "source_type": "ACADEMIC"
      }
    },
    {
      "predicate": "CAPABLE_OF",
      "object": "Through-hole mounting",
      "temporal": {
        "valid_from": "ORIGIN",
        "valid_until": "PRESENT",
        "event": null
      },
      "epistemic": {
        "confidence": 0.7,
        "status": "SETTLED",
        "source_type": "ACADEMIC"
      }
    },
    {
      "predicate": "IS_A",
      "object": "Electronic component package",
      "temporal": {
        "valid_from": null,
        "valid_until": null,
        "event": null
      },
      "epistemic": {
        "confidence": 0.9,
        "status": "SETTLED",
        "source_type": "ACADEMIC"
      }
    },
    {
      "predicate": "HAS_PART",
      "object": "Rectangular housing",
      "temporal": {
        "valid_from": null,
        "valid_until": null,
        "event": null
      },
      "epistemic": {
        "confidence": 1.0,
        "status": "SETTLED",
        "source_type": "ACADEMIC"
      }
    },
    {
      "predicate": "HAS_PART",
      "object": "Two parallel rows of electrical connecting pins",
      "temporal": {
        "valid_from": null,
        "valid_until": null,
        "event": null
      },
      "epistemic": {
        "confidence": 1.0,
        "status": "SETTLED",
        "source_type": "ACADEMIC"
      }
    },
    {
      "predicate": "CAPABLE_OF",
      "object": "Being through-hole mounted to a printed circuit board (PCB)",
      "temporal": {
        "valid_from": null,
        "valid_until": null,
        "event": null
      },
      "epistemic": {
        "confidence": 0.9,
        "status": "SETTLED",
        "source_type": "ACADEMIC"
      }
    },
    {
      "predicate": "CAPABLE_OF",
      "object": "Being inserted in a socket",
      "temporal": {
        "valid_from": null,
        "valid_until": null,
        "event": null
      },
      "epistemic": {
        "confidence": 0.9,
        "status": "SETTLED",
        "source_type": "ACADEMIC"
      }
    },
    {
      "predicate": "MADE_OF",
      "object": "Opaque molded epoxy plastic",
      "temporal": {
        "valid_from": null,
        "valid_until": null,
        "event": null
      },
      "epistemic": {
        "confidence": 0.8,
        "status": "SETTLED",
        "source_type": "ACADEMIC"
      }
    },
    {
      "predicate": "MADE_OF",
      "object": "Tin-plated lead frame",
      "temporal": {
        "valid_from": null,
        "valid_until": null,
        "event": null
      },
      "epistemic": {
        "confidence": 0.8,
        "status": "SETTLED",
        "source_type": "ACADEMIC"
      }
    },
    {
      "predicate": "MADE_OF",
      "object": "Silver-plated lead frame",
      "temporal": {
        "valid_from": null,
        "valid_until": null,
        "event": null
      },
      "epistemic": {
        "confidence": 0.8,
        "status": "SETTLED",
        "source_type": "ACADEMIC"
      }
    },
    {
      "predicate": "MADE_OF",
      "object": "Gold-plated lead frame",
      "temporal": {
        "valid_from": null,
        "valid_until": null,
        "event": null
      },
      "epistemic": {
        "confidence": 0.8,
        "status": "SETTLED",
        "source_type": "ACADEMIC"
      }
    }
  ],
  "surface_layer": {
    "definition": "An electronic component package with a rectangular housing and two parallel rows of electrical connecting pins.",
    "common_uses": [
      "housing integrated circuits",
      "connecting integrated circuits to printed circuit boards"
    ]
  },
  "deep_layer": {
    "mechanism": "Provides a standardized way to connect integrated circuits to other electronic components.",
    "origin": "Invented by Don Forbes, Rex Rice and Bryant Rogers at Fairchild R&D in 1964."
  },
  "instance_layer": {
    "examples": [
      "DIP14 ICs",
      "DIP14N"
    ]
  },
  "facets": {
    "FUNCTION": {
      "roles": [
        "Housing",
        "Electrical Connection"
      ],
      "capabilities": [
        "Protecting integrated circuits",
        "Providing electrical connections"
      ]
    },
    "STRUCTURAL": {
      "visual_features": [
        "Rectangular",
        "Black or Brown"
      ],
      "shape": [
        "Rectangular Prism"
      ],
      "composition": [
        "Plastic",
        "Metal"
      ],
      "parts": [
        "Housing",
        "Pins"
      ]
    }
  },
  "epistemic_metadata": {
    "source": "Set Automatically",
    "citations": [
      "https://en.wikipedia.org/wiki/NC_pin"
    ]
  }
}