{
  "name": "Interstate Conflict",
  "type": "SOCIAL_CONSTRUCT",
  "id": {
    "group": 60,
    "item": 2345
  },
  "claims": [
    {
      "predicate": "IS_A",
      "object": "SOCIAL_EVENT",
      "temporal": {
        "valid_from": "ORIGIN",
        "valid_until": "PRESENT",
        "event": null
      },
      "epistemic": {
        "confidence": 0.9,
        "status": "SETTLED",
        "source_type": "ACADEMIC"
      }
    },
    {
      "predicate": "CAUSES",
      "object": "Socio-Political Instability",
      "temporal": {
        "valid_from": "ORIGIN",
        "valid_until": "PRESENT",
        "event": null
      },
      "epistemic": {
        "confidence": 0.8,
        "status": "SETTLED",
        "source_type": "ACADEMIC"
      }
    }
  ],
  "surface_layer": {
    "definition": "Warfare or other forms of conflict between two or more countries.",
    "common_uses": [
      "Analyzing historical wars",
      "Understanding geopolitical tensions"
    ]
  },
  "deep_layer": {
    "mechanism": "Driven by competing interests or ideologies.",
    "origin": "Often rooted in historical grievances."
  },
  "instance_layer": [],
  "facets": {},
  "epistemic_metadata": {
    "source": "Snippet 1",
    "citations": []
  }
}