{
  "name": "Scalability",
  "type": "ABSTRACT_CONCEPT",
  "id": {
    "group": 50,
    "item": 1012
  },
  "claims": [
    {
      "predicate": "IS_A",
      "object": "ensured by proposed architecture",
      "temporal": {
        "valid_from": "2025",
        "valid_until": "PRESENT",
        "event": "proposed architecture"
      },
      "epistemic": {
        "confidence": 0.7,
        "status": "HYPOTHETICAL",
        "source_type": "ACADEMIC"
      }
    }
  ],
  "surface_layer": {
    "definition": "The ability of a system to handle a growing amount of work or to be readily enlarged.",
    "common_uses": [
      "Handling increased load",
      "Growing efficiently"
    ]
  },
  "deep_layer": {},
  "instance_layer": {},
  "facets": {
    "FUNCTION": {
      "roles": [
        "Growth Management"
      ],
      "capabilities": [
        "Adapting to change",
        "Scaling effectively"
      ]
    }
  },
  "epistemic_metadata": {
    "source": "Design, Implementation and Validation of a Level 2 Automated ...",
    "citations": [
      "https://onlinelibrary.wiley.com/doi/10.1111/exsy.70050"
    ]
  }
}