{
  "name": "\u03b1-Amino-3-hydroxy-5-methyl-4-isoxazolepropionic Acid",
  "type": "INANIMATE_OBJECT",
  "id": {
    "group": 20,
    "item": 1235
  },
  "claims": [
    {
      "predicate": "DEFINED_AS",
      "object": "Specific Agonist for AMPA Receptor",
      "temporal": {
        "valid_from": "ORIGIN",
        "valid_until": "PRESENT",
        "event": null
      },
      "epistemic": {
        "confidence": 0.9,
        "status": "SETTLED",
        "source_type": "ACADEMIC"
      }
    },
    {
      "predicate": "CAPABLE_OF",
      "object": "Mimicking Effects of Glutamate",
      "temporal": {
        "valid_from": "ORIGIN",
        "valid_until": "PRESENT",
        "event": null
      },
      "epistemic": {
        "confidence": 0.8,
        "status": "SETTLED",
        "source_type": "ACADEMIC"
      }
    }
  ],
  "surface_layer": {
    "definition": "\u03b1-Amino-3-hydroxy-5-methyl-4-isoxazolepropionic acid is a compound that is a specific agonist for the AMPA receptor.",
    "common_uses": []
  },
  "deep_layer": {
    "mechanism": "Binds to and activates the AMPA receptor.",
    "origin": null
  },
  "instance_layer": {
    "examples": []
  },
  "facets": {},
  "epistemic_metadata": {
    "source": "Set Automatically",
    "citations": [
      "https://en.wikipedia.org/wiki/AMPA"
    ]
  }
}