{
  "name": "Apical-basal Polarity",
  "type": "ABSTRACT_CONCEPT",
  "id": {
    "group": 50,
    "item": 1006
  },
  "claims": [
    {
      "predicate": "DEFINED_AS",
      "object": "Distinct apical and basolateral compartments in epithelial cells",
      "temporal": {
        "valid_from": "ORIGIN",
        "valid_until": "PRESENT",
        "event": null
      },
      "epistemic": {
        "confidence": 0.9,
        "status": "SETTLED",
        "source_type": "ACADEMIC"
      }
    },
    {
      "predicate": "REQUIRES",
      "object": "Segregation of apical and basolateral plasma membrane domains",
      "temporal": {
        "valid_from": "ORIGIN",
        "valid_until": "PRESENT",
        "event": null
      },
      "epistemic": {
        "confidence": 0.9,
        "status": "SETTLED",
        "source_type": "ACADEMIC"
      }
    },
    {
      "predicate": "ESSENTIAL_FOR",
      "object": "Epithelial cell form",
      "temporal": {
        "valid_from": "ORIGIN",
        "valid_until": "PRESENT",
        "event": null
      },
      "epistemic": {
        "confidence": 0.8,
        "status": "SETTLED",
        "source_type": "ACADEMIC"
      }
    },
    {
      "predicate": "ESSENTIAL_FOR",
      "object": "Epithelial cell function",
      "temporal": {
        "valid_from": "ORIGIN",
        "valid_until": "PRESENT",
        "event": null
      },
      "epistemic": {
        "confidence": 0.8,
        "status": "SETTLED",
        "source_type": "ACADEMIC"
      }
    },
    {
      "predicate": "IS_ESSENTIAL_FOR",
      "object": "epithelial cell form",
      "temporal": {
        "valid_from": "ORIGIN",
        "valid_until": "PRESENT",
        "event": null
      },
      "epistemic": {
        "confidence": 0.9,
        "status": "SETTLED",
        "source_type": "ACADEMIC"
      }
    },
    {
      "predicate": "IS_ESSENTIAL_FOR",
      "object": "epithelial cell function",
      "temporal": {
        "valid_from": "ORIGIN",
        "valid_until": "PRESENT",
        "event": null
      },
      "epistemic": {
        "confidence": 0.9,
        "status": "SETTLED",
        "source_type": "ACADEMIC"
      }
    }
  ],
  "surface_layer": {
    "definition": "The organization of cells into distinct apical and basal domains.",
    "common_uses": []
  },
  "deep_layer": {
    "mechanism": null,
    "origin": null
  },
  "instance_layer": {
    "examples": []
  },
  "facets": {},
  "epistemic_metadata": {
    "source": "Set Automatically",
    "citations": []
  }
}