{
  "name": "Chris Parkes",
  "type": "SOCIAL",
  "id": {
    "group": 61,
    "item": 1007
  },
  "claims": [
    {
      "predicate": "FILLS_ROLE",
      "object": "spokesperson for the collaboration",
      "temporal": {
        "valid_from": "2020",
        "valid_until": "2023",
        "event": "Succession"
      },
      "epistemic": {
        "confidence": 1.0,
        "status": "HISTORICAL",
        "source_type": "ACADEMIC"
      }
    }
  ],
  "surface_layer": {
    "definition": "Former spokesperson for the LHCb collaboration.",
    "common_uses": []
  },
  "deep_layer": {
    "mechanism": null,
    "origin": null
  },
  "instance_layer": {
    "examples": []
  },
  "facets": {},
  "epistemic_metadata": {
    "source": "LHCb experiment",
    "citations": [
      "https://en.wikipedia.org/wiki/LHCb_experiment"
    ]
  }
}