{
  "name": "ingestion dynamics",
  "type": "ABSTRACT_CONCEPT",
  "id": {
    "group": 50,
    "item": 1003
  },
  "claims": [],
  "surface_layer": {
    "definition": "The processes and patterns related to the intake of substances by organisms.",
    "common_uses": []
  },
  "deep_layer": {
    "mechanism": null,
    "origin": null
  },
  "instance_layer": {
    "examples": []
  },
  "facets": {},
  "epistemic_metadata": {
    "source": "https://www.sciencedirect.com/science/article/pii/S2666821126000116",
    "citations": []
  }
}