{
  "name": "Neuroanesthesia",
  "type": "ABSTRACT_CONCEPT",
  "id": {
    "group": 50,
    "item": 1007
  },
  "claims": [],
  "surface_layer": {
    "definition": "Anesthesia specific to neurological procedures.",
    "common_uses": []
  },
  "deep_layer": {
    "mechanism": "Unknown",
    "origin": "Evolved from general anesthesia principles, adapted for the nervous system."
  },
  "instance_layer": {
    "examples": []
  },
  "facets": {},
  "epistemic_metadata": {
    "source": "Set Automatically",
    "citations": []
  }
}