{
  "name": "Sex Steroid Hormones",
  "type": "ABSTRACT_CONCEPT",
  "id": {
    "group": 50,
    "item": 1001
  },
  "claims": [
    {
      "predicate": "MADE_OF",
      "object": "Cholesterol",
      "temporal": {
        "valid_from": "ORIGIN",
        "valid_until": "PRESENT",
        "event": null
      },
      "epistemic": {
        "confidence": 0.8,
        "status": "SETTLED",
        "source_type": "ACADEMIC"
      }
    },
    {
      "predicate": "CAUSES",
      "object": "Pleiotropic effects",
      "temporal": {
        "valid_from": "ORIGIN",
        "valid_until": "PRESENT",
        "event": null
      },
      "epistemic": {
        "confidence": 0.7,
        "status": "SETTLED",
        "source_type": "ACADEMIC"
      }
    },
    {
      "predicate": "LOCATED_AT",
      "object": "Central nervous system",
      "temporal": {
        "valid_from": "ORIGIN",
        "valid_until": "PRESENT",
        "event": null
      },
      "epistemic": {
        "confidence": 0.8,
        "status": "SETTLED",
        "source_type": "ACADEMIC"
      }
    },
    {
      "predicate": "DEFINED_AS",
      "object": "Steroid hormones",
      "temporal": {
        "valid_from": null,
        "valid_until": null,
        "event": null
      },
      "epistemic": {
        "confidence": 0.9,
        "status": "SETTLED",
        "source_type": "ACADEMIC"
      }
    },
    {
      "predicate": "CAPABLE_OF",
      "object": "regulation of various processes in the cardiovascular system",
      "temporal": {
        "valid_from": null,
        "valid_until": null,
        "event": null
      },
      "epistemic": {
        "confidence": 0.8,
        "status": "SETTLED",
        "source_type": "ACADEMIC"
      }
    },
    {
      "predicate": "CAPABLE_OF",
      "object": "regulation of various processes in the immune system",
      "temporal": {
        "valid_from": null,
        "valid_until": null,
        "event": null
      },
      "epistemic": {
        "confidence": 0.8,
        "status": "SETTLED",
        "source_type": "ACADEMIC"
      }
    },
    {
      "predicate": "CAPABLE_OF",
      "object": "regulation of various processes in the muscular system",
      "temporal": {
        "valid_from": null,
        "valid_until": null,
        "event": null
      },
      "epistemic": {
        "confidence": 0.8,
        "status": "SETTLED",
        "source_type": "ACADEMIC"
      }
    },
    {
      "predicate": "CAPABLE_OF",
      "object": "regulation of various processes in the neural system",
      "temporal": {
        "valid_from": null,
        "valid_until": null,
        "event": null
      },
      "epistemic": {
        "confidence": 0.8,
        "status": "SETTLED",
        "source_type": "ACADEMIC"
      }
    },
    {
      "predicate": "CAPABLE_OF",
      "object": "affecting prenatal development of various brain structures",
      "temporal": {
        "valid_from": null,
        "valid_until": null,
        "event": null
      },
      "epistemic": {
        "confidence": 0.8,
        "status": "SETTLED",
        "source_type": "ACADEMIC"
      }
    },
    {
      "predicate": "CAPABLE_OF",
      "object": "affecting postnatal development of various brain structures",
      "temporal": {
        "valid_from": null,
        "valid_until": null,
        "event": null
      },
      "epistemic": {
        "confidence": 0.8,
        "status": "SETTLED",
        "source_type": "ACADEMIC"
      }
    }
  ],
  "surface_layer": {
    "definition": "Steroid hormones involved in sexual development and reproduction.",
    "common_uses": []
  },
  "deep_layer": {
    "mechanism": "Act via nuclear receptors to regulate gene expression.",
    "origin": "Synthesized from cholesterol."
  },
  "instance_layer": {
    "examples": []
  },
  "facets": {},
  "epistemic_metadata": {
    "source": "Set Automatically",
    "citations": []
  }
}